json_config_validator/__init__.py
json_config_validator/main.py
json_config_validator/json/__init__.py
json_config_validator/json/schema/__init__.py
json_config_validator/json/schema/validator.py
json_config_validator/terminal/__init__.py
json_config_validator/terminal/color_utils.py
json_config_validator-0.1.0.dist-info/AUTHORS.rst
json_config_validator-0.1.0.dist-info/LICENSE
json_config_validator-0.1.0.dist-info/METADATA
json_config_validator-0.1.0.dist-info/WHEEL
json_config_validator-0.1.0.dist-info/entry_points.txt
json_config_validator-0.1.0.dist-info/top_level.txt
json_config_validator-0.1.0.dist-info/RECORD
