Metadata-Version: 2.1
Name: json-config-validator
Version: 0.1.0
Summary: Package for validation JSON configuration files
Home-page: https://github.com/jai-python3/json-config-validator
Author: Jaideep Sundaram
Author-email: jai.python3@gmail.com
License: GNU General Public License v3
Keywords: json_config_validator
Classifier: Development Status :: 2 - Pre-Alpha
Classifier: Intended Audience :: Developers
Classifier: License :: OSI Approved :: GNU General Public License v3 (GPLv3)
Classifier: Natural Language :: English
Classifier: Programming Language :: Python :: 3
Classifier: Programming Language :: Python :: 3.6
Classifier: Programming Language :: Python :: 3.7
Classifier: Programming Language :: Python :: 3.8
Requires-Python: >=3.6
License-File: LICENSE
License-File: AUTHORS.rst
Requires-Dist: Click >=7.0
Requires-Dist: jsonschema
Requires-Dist: colorama
